<annotation>
	<folder>kongdong</folder>
	<filename>0009.jpg</filename>
	<path>C:\Users\17333\Desktop\data\kongdong\0009.jpg</path>
	<source>
		<database>Unknown</database>
	</source>
	<size>
		<width>748</width>
		<height>1920</height>
		<depth>3</depth>
	</size>
	<segmented>0</segmented>
	<object>
		<name>kongdong</name>
		<pose>Unspecified</pose>
		<truncated>0</truncated>
		<difficult>0</difficult>
		<bndbox>
			<xmin>333</xmin>
			<ymin>481</ymin>
			<xmax>424</xmax>
			<ymax>565</ymax>
		</bndbox>
	</object>
	<object>
		<name>kongdong</name>
		<pose>Unspecified</pose>
		<truncated>0</truncated>
		<difficult>0</difficult>
		<bndbox>
			<xmin>28</xmin>
			<ymin>1611</ymin>
			<xmax>92</xmax>
			<ymax>1690</ymax>
		</bndbox>
	</object>
</annotation>
